package_publishing_example/__init__.py
package_publishing_example/cli.py
package_publishing_example/revcomp.py
package_publishing_example-0.0.4.dist-info/METADATA
package_publishing_example-0.0.4.dist-info/WHEEL
package_publishing_example-0.0.4.dist-info/entry_points.txt
package_publishing_example-0.0.4.dist-info/licenses/LICENSE
package_publishing_example-0.0.4.dist-info/RECORD
