Metadata-Version: 2.4
Name: package-publishing-example
Version: 0.0.4
Summary: Add your description here
Author-email: Rens Holmer <8225367+holmrenser@users.noreply.github.com>
License-File: LICENSE
Requires-Python: >=3.10
Requires-Dist: pytest>=8.3.5
Requires-Dist: ruff>=0.11.0
Requires-Dist: typer>=0.15.2
Requires-Dist: uv-dynamic-versioning>=0.6.0
